cache2q/__init__.py
cache2q/cache2q.py
cache2q-0.1.0.dist-info/licenses/LICENSE
cache2q-0.1.0.dist-info/METADATA
cache2q-0.1.0.dist-info/WHEEL
cache2q-0.1.0.dist-info/top_level.txt
cache2q-0.1.0.dist-info/RECORD
